_case.cpython-39-i386-linux-gnu.so
__init__.py
yascc-0.3.23.dist-info/top_level.txt
yascc-0.3.23.dist-info/METADATA
yascc-0.3.23.dist-info/LICENSE
yascc-0.3.23.dist-info/RECORD
yascc-0.3.23.dist-info/WHEEL
yascc/case.c
yascc/__init__.py
yascc/snakecase.py
yascc/camelcase.py
yascc/common.py
