Metadata-Version: 2.1
Name: yascc
Version: 0.3.23
Summary: Yet another string case converter
Author-email: urm8 <arctgisnil@gmail.com>
License: DTFYW
Project-URL: Homepage, https://github.com/urm8/yascc
Project-URL: Repository, https://github.com/urm8/yascc
Classifier: Topic :: Utilities
Classifier: Programming Language :: Python :: 3
Classifier: Programming Language :: Python :: 3.7
Classifier: Programming Language :: Python :: 3.8
Classifier: Programming Language :: Python :: 3.9
Classifier: Programming Language :: Python :: 3.10
Requires-Python: >=3.7
License-File: LICENSE
